pywinauto_recorder/__init__.py
pywinauto_recorder/core.py
pywinauto_recorder/element_observer.py
pywinauto_recorder/ocr_wrapper.py
pywinauto_recorder/player.py
pywinauto_recorder/recorder.py
pywinauto_recorder/Icons/IconPyRec.ico
pywinauto_recorder/Icons/check.ico
pywinauto_recorder/Icons/comments.ico
pywinauto_recorder/Icons/cross.ico
pywinauto_recorder/Icons/favourite.ico
pywinauto_recorder/Icons/folder.ico
pywinauto_recorder/Icons/help.ico
pywinauto_recorder/Icons/light-on.ico
pywinauto_recorder/Icons/paste.ico
pywinauto_recorder/Icons/play.ico
pywinauto_recorder/Icons/power.ico
pywinauto_recorder/Icons/record.ico
pywinauto_recorder/Icons/search.ico
pywinauto_recorder/Icons/settings.ico
pywinauto_recorder/Icons/stop.ico
pywinauto_recorder-0.6.8.dist-info/LICENSE
pywinauto_recorder-0.6.8.dist-info/METADATA
pywinauto_recorder-0.6.8.dist-info/WHEEL
pywinauto_recorder-0.6.8.dist-info/top_level.txt
pywinauto_recorder-0.6.8.dist-info/RECORD
