Metadata-Version: 2.1
Name: pywinauto_recorder
Version: 0.6.8
Summary: Records/Replays GUI actions
Home-page: https://github.com/beuaaa/pywinauto_recorder
Author: david pratmarty
Author-email: david.pratmarty@gmail.com
License: MIT
Project-URL: Documentation, https://pywinauto-recorder.readthedocs.io
Project-URL: Source, https://github.com/beuaaa/pywinauto_recorder
Classifier: Development Status :: 5 - Production/Stable
Classifier: Environment :: Console
Classifier: Environment :: Win32 (MS Windows)
Classifier: Intended Audience :: End Users/Desktop
Classifier: Intended Audience :: Developers
Classifier: License :: OSI Approved :: MIT License
Classifier: Operating System :: Microsoft :: Windows
Classifier: Programming Language :: Python
Classifier: Programming Language :: Python :: 3.8
Classifier: Topic :: Software Development :: Libraries :: Python Modules
Classifier: Topic :: Software Development :: Testing
Classifier: Topic :: Software Development :: User Interfaces
Classifier: Topic :: Software Development :: Quality Assurance
License-File: LICENSE
Requires-Dist: pywinauto
Requires-Dist: keyboard
Requires-Dist: mouse
Requires-Dist: overlay_arrows_and_more
Requires-Dist: enum34
Requires-Dist: pyperclip
Requires-Dist: cachetools
Requires-Dist: thefuzz
Requires-Dist: Pillow
